trd.py
traduire_cli-0.0.5.dist-info/METADATA
traduire_cli-0.0.5.dist-info/WHEEL
traduire_cli-0.0.5.dist-info/entry_points.txt
traduire_cli-0.0.5.dist-info/top_level.txt
traduire_cli-0.0.5.dist-info/RECORD
