Metadata-Version: 2.1
Name: traduire-cli
Version: 0.0.5
Summary: Traduire CLI
Author-email: Matthias Kestenholz <mk@feinheit.ch>
Project-URL: Bug Tracker, https://github.com/matthiask/traduire/issues
Project-URL: Homepage, https://github.com/matthiask/traduire
Classifier: Programming Language :: Python :: 3 :: Only
Classifier: Programming Language :: Python :: 3.12
Requires-Python: >=3.12
Requires-Dist: click
Requires-Dist: requests
